{"created_at": "2026-04-07T21:10:10.113345+08:00", "train_time": 1812, "train_step": 2094, "platform": "tencent_kaiwu", "business": "competition", "user_id": 1, "team_id": 2, "project_code": "robot_vacuum", "project_version": "13.0.1", "task_id": "uuid", "algorithm": "ppo", "model_file_name": "robot_vacuum-ppo-2094-2026_04_07_21_10_10-13.0.1.zip", "model_file_hash": "7578835a1a29348423c7f92a50276e640b8988ae342b116902cb35397945cf67", "model_file_path": ["ckpt/model.ckpt-2094.pkl"], "signature": null}